setup.py
clplot/__init__.py
clplot/clplot.py
clplot/data_handler.py
clplot/globe.py
clplot/helpers.py
clplot/plot.py
clplot/structure.py
commandlineplot.egg-info/PKG-INFO
commandlineplot.egg-info/SOURCES.txt
commandlineplot.egg-info/dependency_links.txt
commandlineplot.egg-info/entry_points.txt
commandlineplot.egg-info/requires.txt
commandlineplot.egg-info/top_level.txt