Metadata-Version: 1.1
Name: commandlineplot
Version: 0.1
Summary: a command line plotting utility written in python
Home-page: http://github.com/JohnFNovak/clplot/
Author: John F Novak
Author-email: john.franc.novak@gmail.com
License: Public Domain
Platform: any
Classifier: Programming Language :: Python
Classifier: Development Status :: 4 - Beta
Classifier: Natural Language :: English
Classifier: Environment :: Console
Classifier: Intended Audience :: Science/Research
Classifier: License :: Public Domain
Classifier: Operating System :: OS Independent
Classifier: Topic :: Scientific/Engineering :: Visualization
